richlib/__init__.py
richlib/basic_lighting.fs
richlib/basic_lighting.vs
richlib/rlights.py
richlib/util.py
richlib/models/barracks.obj
richlib/models/barracks_diffuse.png
richlib/models/bridge.obj
richlib/models/bridge_diffuse.png
richlib/models/castle.obj
richlib/models/castle_diffuse.png
richlib/models/church.obj
richlib/models/church_diffuse.png
richlib/models/house.obj
richlib/models/house_diffuse.png
richlib/models/market.obj
richlib/models/market_diffuse.png
richlib/models/trooper.obj
richlib/models/trooper_ao.png
richlib/models/trooper_diffuse.png
richlib/models/trooper_metalness.png
richlib/models/trooper_normals.png
richlib/models/trooper_roughness.png
richlib/models/turret.obj
richlib/models/turret_diffuse.png
richlib/models/watermill.obj
richlib/models/watermill_diffuse.png
richlib/models/well.obj
richlib/models/well_diffuse.png
richlib-0.0.6.dist-info/LICENSE
richlib-0.0.6.dist-info/METADATA
richlib-0.0.6.dist-info/WHEEL
richlib-0.0.6.dist-info/top_level.txt
richlib-0.0.6.dist-info/RECORD
