Metadata-Version: 2.1
Name: richlib
Version: 0.0.6
Summary: Pygame Zero like API to teach 3d games programming based on Raylib
Home-page: https://github.com/electronstudio/richlib
Author: Electron Studio
Author-email: github@electronstudio.co.uk
License: LGPLv3+
Platform: UNKNOWN
Classifier: License :: OSI Approved :: GNU Lesser General Public License v3 or later (LGPLv3+)
Classifier: Programming Language :: Python :: 3
Classifier: Programming Language :: Python :: 3.5
Classifier: Programming Language :: Python :: 3.6
Classifier: Programming Language :: Python :: 3.7
Requires-Dist: raylib (>=2.5.0.post4)
Requires-Dist: cffi (>=1.12.3)
